dbcp_lite.py
dbcp_lite-0.0.2.dist-info/LICENSE
dbcp_lite-0.0.2.dist-info/METADATA
dbcp_lite-0.0.2.dist-info/WHEEL
dbcp_lite-0.0.2.dist-info/top_level.txt
dbcp_lite-0.0.2.dist-info/RECORD
