Metadata-Version: 2.1
Name: dbcp-lite
Version: 0.0.2
Summary: Simple, light and nearly featureless database connection pool
Home-page: https://github.com/jowage58/dbcp_lite/
Author: John Wagenleitner
Author-email: johnwa@mail.fresnostate.edu
License: UNKNOWN
Project-URL: Bug Reports, https://github.com/jowage58/dbcp_lite/issues
Project-URL: Source, https://github.com/jowage58/dbcp_lite/
Keywords: database connection pool
Platform: UNKNOWN
Classifier: Development Status :: 3 - Alpha
Classifier: License :: OSI Approved :: Apache Software License
Classifier: Topic :: Database
Classifier: Intended Audience :: Developers
Classifier: Programming Language :: Python :: 3
Classifier: Programming Language :: Python :: 3.6
Classifier: Programming Language :: Python :: 3.7
Classifier: Programming Language :: Python :: 3.8
Requires-Python: >=3.6, <4
